skwiz_logger_python/__init__.py
skwiz_logger_python/colors.py
skwiz_logger_python/config.py
skwiz_logger_python/error.py
skwiz_logger_python/formatter.py
skwiz_logger_python/handler_udp.py
skwiz_logger_python/logger.py
skwiz_logger_python-0.13.0.dist-info/METADATA
skwiz_logger_python-0.13.0.dist-info/WHEEL
skwiz_logger_python-0.13.0.dist-info/RECORD
