Metadata-Version: 2.1
Name: skwiz-logger-python
Version: 0.13.0
Summary: A skwiz logger for python projects
Author: hmoumal
Author-email: henri.moumal@sagacify.com
Requires-Python: >=3.10,<4.0
Classifier: Programming Language :: Python :: 3
Classifier: Programming Language :: Python :: 3.10
Classifier: Programming Language :: Python :: 3.11
Classifier: Programming Language :: Python :: 3.12
